clockngpn
