Metadata-Version: 2.1
Name: c-lock
Version: 0.0.7.5
Summary: A TOTP based next generation port knocking service.
Home-page: https://gitlab.com/junquera/c-lock
Author: Javier Junquera Sánchez
Author-email: javier@junquera.xyz
License: MIT License
Platform: UNKNOWN
Requires-Python: >=3.6
